apm/__init__.py
apm/api.py
apm/server.py
apm/tk.py
alia_apm-0.1.18.1.dist-info/METADATA
alia_apm-0.1.18.1.dist-info/WHEEL
alia_apm-0.1.18.1.dist-info/top_level.txt
alia_apm-0.1.18.1.dist-info/RECORD
