Metadata-Version: 2.4
Name: alia-apm
Version: 0.1.18.1
Summary: A collection of Python scripts by me, Alia.
Home-page: https://github.com/AbnormalNormality/apm
Author: Alia Normal
Author-email: dan.driscoll@aussiebb.com
License: MIT
Classifier: Programming Language :: Python :: 3
Classifier: License :: OSI Approved :: MIT License
Classifier: Operating System :: OS Independent
Requires-Python: >=3.12
Requires-Dist: discord>=2.0
Requires-Dist: twitchio
Dynamic: author
Dynamic: author-email
Dynamic: classifier
Dynamic: description
Dynamic: description-content-type
Dynamic: home-page
Dynamic: license
Dynamic: requires-dist
Dynamic: requires-python
Dynamic: summary
